Metadata-Version: 2.1
Name: nbdev-cards-nix-flake
Version: 0.0.1
Summary: Modelling GNN following LAIDD tutorial
Home-page: https://github.com/sepiabrown/nbdev_cards/
Author: Suwon Park
Author-email: bboxone@gmail.com
License: Apache Software License 2.0
Keywords: nbdev
Platform: UNKNOWN
Classifier: Development Status :: 3 - Alpha
Classifier: Intended Audience :: Developers
Classifier: Natural Language :: English
Classifier: Programming Language :: Python :: 3.9
Classifier: Programming Language :: Python :: 3.10
Classifier: License :: OSI Approved :: Apache Software License
Requires-Python: >=3.9
License-File: LICENSE
Requires-Dist: fastcore
Requires-Dist: pandas
Requires-Dist: pytz
Provides-Extra: dev
